vggish_keras/__init__.py
vggish_keras/params.py
vggish_keras/postprocess.py
vggish_keras/pump.py
vggish_keras/vggish.py
vggish_keras-0.0.3.dist-info/LICENSE
vggish_keras-0.0.3.dist-info/METADATA
vggish_keras-0.0.3.dist-info/WHEEL
vggish_keras-0.0.3.dist-info/top_level.txt
vggish_keras-0.0.3.dist-info/RECORD
