Metadata-Version: 2.1
Name: vggish-keras
Version: 0.0.3
Summary: VGGish in Keras.
Home-page: https://github.com/beasteers/VGGish
Author: Bea Steers
Author-email: bea.steers@gmail.com
License: MIT License
Keywords: vggish audio audioset keras tensorflow
Platform: UNKNOWN
Classifier: License :: OSI Approved :: ISC License (ISCL)
Classifier: Programming Language :: Python
Classifier: Development Status :: 3 - Alpha
Classifier: Intended Audience :: Developers
Classifier: Topic :: Software Development
Classifier: Programming Language :: Python :: 3
Classifier: Programming Language :: Python :: 3.5
Classifier: Programming Language :: Python :: 3.6
Classifier: Programming Language :: Python :: 3.7
Requires-Dist: numpy
Requires-Dist: tensorflow (<=1.14)
Requires-Dist: pumpp
